pretix_quickpay/__init__.py
pretix_quickpay/apps.py
pretix_quickpay/payment.py
pretix_quickpay/paymentmethods.py
pretix_quickpay/signals.py
pretix_quickpay/urls.py
pretix_quickpay/views.py
pretix_quickpay/locale/de/LC_MESSAGES/django.mo
pretix_quickpay/locale/de/LC_MESSAGES/django.po
pretix_quickpay/locale/de_Informal/.gitkeep
pretix_quickpay/locale/de_Informal/LC_MESSAGES/django.mo
pretix_quickpay/locale/de_Informal/LC_MESSAGES/django.po
pretix_quickpay/static/pretix_quickpay/.gitkeep
pretix_quickpay/static/pretix_quickpay/logo.svg
pretix_quickpay/templates/pretix_quickpay/.gitkeep
pretix_quickpay/templates/pretix_quickpay/checkout_payment_confirm.html
pretix_quickpay/templates/pretix_quickpay/checkout_payment_form.html
pretix_quickpay/templates/pretix_quickpay/control.html
pretix_quickpay/templates/pretix_quickpay/pending.html
pretix_unzerdirect/__init__.py
pretix_unzerdirect/apps.py
pretix_unzerdirect/payment.py
pretix_unzerdirect/paymentmethods.py
pretix_unzerdirect/signals.py
pretix_unzerdirect/urls.py
pretix_unzerdirect/locale/de/LC_MESSAGES/django.mo
pretix_unzerdirect/locale/de/LC_MESSAGES/django.po
pretix_unzerdirect/locale/de_Informal/.gitkeep
pretix_unzerdirect/locale/de_Informal/LC_MESSAGES/django.mo
pretix_unzerdirect/locale/de_Informal/LC_MESSAGES/django.po
pretix_unzerdirect/static/pretix_unzerdirect/.gitkeep
pretix_unzerdirect/static/pretix_unzerdirect/logo.svg
pretix_unzerdirect/templates/pretix_unzerdirect/.gitkeep
pretix_quickpay-1.1.2.dist-info/LICENSE
pretix_quickpay-1.1.2.dist-info/METADATA
pretix_quickpay-1.1.2.dist-info/WHEEL
pretix_quickpay-1.1.2.dist-info/entry_points.txt
pretix_quickpay-1.1.2.dist-info/top_level.txt
pretix_quickpay-1.1.2.dist-info/RECORD
