Metadata-Version: 2.1
Name: pretix-quickpay
Version: 1.1.2
Summary: Use Quickpay as a payment provider, where you can activate various payment methods for your customers.
Author-email: pretix team <support@pretix.eu>
Maintainer-email: pretix team <support@pretix.eu>
License: 
Project-URL: homepage, https://github.com/pretix/pretix-quickpay
Keywords: pretix
Requires-Python: >=3.9
License-File: LICENSE
Requires-Dist: quickpay-api-client ==2.0.*
